bonegame/__init__.py
bonegame/game.py
bonegame/gobang.py
bonegame/core/__init__.py
bonegame/core/board.py
bonegame/core/player.py
bonegame/renderers/__init__.py
bonegame/renderers/renderer.py
bone_games-0.1.1.dist-info/LICENSE
bone_games-0.1.1.dist-info/METADATA
bone_games-0.1.1.dist-info/WHEEL
bone_games-0.1.1.dist-info/top_level.txt
bone_games-0.1.1.dist-info/RECORD
