Metadata-Version: 2.1
Name: bone-games
Version: 0.1.1
Summary: 基于OpenCV的各种小游戏
Home-page: UNKNOWN
Author: zrr
Author-email: 2742392377@qq.com
License: GPL-3.0 Licence
Keywords: GoBang,Game
Platform: any
Classifier: Programming Language :: Python :: 3
Classifier: License :: OSI Approved :: GNU Lesser General Public License v3 (LGPLv3)
Classifier: Operating System :: OS Independent
Requires-Dist: numpy
Requires-Dist: opencv-python
Requires-Dist: taichi
